caf/space/__init__.py
caf/space/__main__.py
caf/space/_version.py
caf/space/inputs.py
caf/space/metadata.py
caf/space/py.typed
caf/space/ui.py
caf/space/utils.py
caf/space/weighted_funcs.py
caf/space/zone_correspondence.py
caf/space/zone_translation.py
caf_space-1.6.2.dist-info/licenses/LICENSE
caf_space-1.6.2.dist-info/METADATA
caf_space-1.6.2.dist-info/WHEEL
caf_space-1.6.2.dist-info/entry_points.txt
caf_space-1.6.2.dist-info/top_level.txt
caf_space-1.6.2.dist-info/RECORD
