Metadata-Version: 2.4
Name: caf.space
Version: 1.6.2
Summary: Easily generate translations between zoning systems
Author: Transport for the North
License: Copyright © Transport for the North (“TfN”) (2023).
Project-URL: Bug Tracker, https://github.com/Transport-for-the-North/caf.space/issues
Project-URL: Homepage, https://github.com/Transport-for-the-North/caf.space
Project-URL: Source, https://github.com/Transport-for-the-North/caf.space
Project-URL: Documentation, http://cafspace.rtfd.io/
Classifier: Programming Language :: Python :: 3 :: Only
Classifier: Programming Language :: Python :: 3.10
Classifier: Programming Language :: Python :: 3.11
Classifier: Programming Language :: Python :: 3.12
Classifier: Programming Language :: Python :: 3.13
Requires-Python: >=3.9
License-File: LICENSE
Requires-Dist: caf.toolkit>=0.2.1
Requires-Dist: geopandas>=1
Requires-Dist: fiona>=1.8
Requires-Dist: shapely>=1.8
Requires-Dist: numpy>=1.21
Requires-Dist: pandas>=1.3
Requires-Dist: pydantic>=2.0.0
Requires-Dist: openpyxl>=3.0
Requires-Dist: scipy>=1.12
Provides-Extra: dev
Requires-Dist: black>=22.6.0; extra == "dev"
Requires-Dist: mypy<2.0.0,>=1.0.0; extra == "dev"
Requires-Dist: mypy_extensions<2.0.0,>=1.0.0; extra == "dev"
Requires-Dist: pydocstyle[toml]>=6.1.1; extra == "dev"
Requires-Dist: pylint>=2.14.5; extra == "dev"
Requires-Dist: pytest<8.0.0,>=7.4.0; extra == "dev"
Requires-Dist: pytest-cov<5.0.0,>=4.1.0; extra == "dev"
Requires-Dist: pytest-xdist<4.0.0,>=3.3.1; extra == "dev"
Requires-Dist: tox<4.0.0,>=3.24.3; extra == "dev"
Requires-Dist: versioningit<3.0.0,>=2.2.0; extra == "dev"
Provides-Extra: docs
Requires-Dist: sphinx>=7.1.2; extra == "docs"
Requires-Dist: pydata-sphinx-theme>=0.14.1; extra == "docs"
Requires-Dist: graphviz>=0.20.1; extra == "docs"
Requires-Dist: sphinx-gallery>=0.17.1; extra == "docs"
Requires-Dist: matplotlib; extra == "docs"
Requires-Dist: sphinx-argparse>=0.5.2; extra == "docs"
Dynamic: license-file
